README.md
setup.cfg
setup.py
Topsis_Yoshna_101903502.egg-info/PKG-INFO
Topsis_Yoshna_101903502.egg-info/SOURCES.txt
Topsis_Yoshna_101903502.egg-info/dependency_links.txt
Topsis_Yoshna_101903502.egg-info/entry_points.txt
Topsis_Yoshna_101903502.egg-info/requires.txt
Topsis_Yoshna_101903502.egg-info/top_level.txt
topsis_python/topsis.py