Metadata-Version: 2.1
Name: Topsis-Yoshna-101903502
Version: 1.0.0
Summary: A Python package implementing TOPSIS technique.
Home-page: UNKNOWN
Author: Yoshna Marwaha
Author-email: ymarwaha_be19@thapar.edu
License: MIT
Platform: UNKNOWN
Classifier: License :: OSI Approved :: MIT License
Classifier: Programming Language :: Python :: 3
Classifier: Programming Language :: Python :: 3.7
